neuralogic/__init__.py
neuralogic/__version__.py
neuralogic/core/__init__.py
neuralogic/core/enums.py
neuralogic/core/sources.py
neuralogic/core/template.py
neuralogic/core/builder/__init__.py
neuralogic/core/builder/builder.py
neuralogic/core/builder/components.py
neuralogic/core/builder/dataset_builder.py
neuralogic/core/constructs/__init__.py
neuralogic/core/constructs/factories.py
neuralogic/core/constructs/java_objects.py
neuralogic/core/constructs/metadata.py
neuralogic/core/constructs/predicate.py
neuralogic/core/constructs/relation.py
neuralogic/core/constructs/rule.py
neuralogic/core/constructs/term.py
neuralogic/core/constructs/function/__init__.py
neuralogic/core/constructs/function/concat.py
neuralogic/core/constructs/function/enum.py
neuralogic/core/constructs/function/function.py
neuralogic/core/constructs/function/function_container.py
neuralogic/core/constructs/function/function_graph.py
neuralogic/core/constructs/function/reshape.py
neuralogic/core/constructs/function/slice.py
neuralogic/core/constructs/function/softmax.py
neuralogic/core/settings/__init__.py
neuralogic/core/settings/settings_proxy.py
neuralogic/dataset/__init__.py
neuralogic/dataset/base.py
neuralogic/dataset/csv.py
neuralogic/dataset/db.py
neuralogic/dataset/file.py
neuralogic/dataset/logic.py
neuralogic/dataset/tensor.py
neuralogic/db/__init__.py
neuralogic/db/converter.py
neuralogic/db/pg/__init__.py
neuralogic/db/pg/helpers.py
neuralogic/inference/__init__.py
neuralogic/inference/evaluation_inference_engine.py
neuralogic/inference/inference_engine.py
neuralogic/jar/NeuraLogic.jar
neuralogic/jar/__init__.py
neuralogic/logging/__init__.py
neuralogic/nn/__init__.py
neuralogic/nn/base.py
neuralogic/nn/init.py
neuralogic/nn/java.py
neuralogic/nn/loss.py
neuralogic/nn/torch_function.py
neuralogic/nn/evaluator/__init__.py
neuralogic/nn/evaluator/java.py
neuralogic/nn/module/__init__.py
neuralogic/nn/module/module.py
neuralogic/nn/module/general/__init__.py
neuralogic-0.8.0.dist-info/LICENSE
neuralogic-0.8.0.dist-info/METADATA
neuralogic-0.8.0.dist-info/WHEEL
neuralogic-0.8.0.dist-info/top_level.txt
neuralogic-0.8.0.dist-info/RECORD
