Metadata-Version: 2.1
Name: neuralogic
Version: 0.8.0
Summary: PyNeuraLogic lets you use Python to create Differentiable Logic Programs.
Home-page: https://github.com/LukasZahradnik/PyNeuraLogic
Author: Lukáš Zahradník
Author-email: lukaszahradnik96@seznam.cz
License: MIT
Classifier: License :: OSI Approved :: MIT License
Classifier: Development Status :: 4 - Beta
Classifier: Intended Audience :: Science/Research
Classifier: Intended Audience :: Developers
Classifier: Intended Audience :: Education
Classifier: Programming Language :: Python
Classifier: Programming Language :: Python :: 3
Classifier: Programming Language :: Python :: 3.8
Classifier: Programming Language :: Python :: 3.9
Classifier: Programming Language :: Python :: 3.10
Classifier: Topic :: Scientific/Engineering :: Artificial Intelligence
Requires-Python: >=3.7.0
License-File: LICENSE
Requires-Dist: JPype1>=1.3.0
Requires-Dist: numpy>=1.20.4
Requires-Dist: matplotlib
Requires-Dist: tqdm
